{
  "file": "ha-frigate-privacy.js",
  "size_kb": 82.0,
  "lines": 2272,
  "has_iife": true,
  "iife_closes": false,
  "custom_element": "ha-frigate-privacy",
  "has_ce_guard": true,
  "class_name": "HaFrigatePrivacy",
  "has_shadow_dom": true,
  "has_bento_css": true,
  "has_hass_guard": true,
  "uses_xss_escape": true,
  "innerHTML_count": 2,
  "xss_escape_calls": 1,
  "has_pl": true,
  "has_en": true,
  "translation_keys_sample": [],
  "tabs": [
    "history",
    "schedule",
    "control",
    "settings"
  ],
  "ws_calls": [
    "timer/create",
    "automation/config",
    "input_text/create"
  ],
  "service_calls": [
    "input_text",
    "persistent_notification",
    "switch",
    "timer",
    "automation"
  ],
  "fetch_urls": [],
  "get_settings": [],
  "set_settings": [],
  "localStorage_keys": [
    "ha-tools-"
  ],
  "uses_persistence": true,
  "has_card_class": true,
  "has_container_class": false,
  "has_dark_mode": true,
  "has_responsive": true,
  "breakpoints": [
    "480",
    "800",
    "768"
  ],
  "try_catch_count": 29,
  "console_error_count": 3,
  "addEventListener_count": 24,
  "removeEventListener_count": 0,
  "has_disconnectedCallback": true,
  "methods_sample": [
    "constructor",
    "super",
    "getCardSize",
    "_sanitize",
    "if",
    "setConfig",
    "setTimeout",
    "disconnectedCallback",
    "clearInterval",
    "_updateFrigateStatus",
    "_detectCameras",
    "_parseFrigateVersion",
    "_detectFrigateVersion",
    "for",
    "_checkFrigateSupport",
    "_storageKey",
    "_loadSchedules",
    "_saveSchedules",
    "_loadHistory",
    "_saveHistory",
    "_loadNotifySettings",
    "_saveNotifySettings",
    "_savePrivacyState",
    "_loadPrivacyState",
    "_applyPrivacyState",
    "_getCameraLabel",
    "_addHistoryEntry",
    "_checkSchedules",
    "_startCountdown",
    "_updateCountdownDisplay"
  ]
}